arp_policy/__init__.py
arp_policy/audit.py
arp_policy/enforcer.py
arp_policy/errors.py
arp_policy/policy.py
arp_policy/py.typed
arp_policy/utils.py
arp_policy-0.1.2.dist-info/licenses/LICENSE
arp_policy-0.1.2.dist-info/METADATA
arp_policy-0.1.2.dist-info/WHEEL
arp_policy-0.1.2.dist-info/top_level.txt
arp_policy-0.1.2.dist-info/RECORD
