Metadata-Version: 2.4
Name: arp-policy
Version: 0.1.2
Summary: Policy evaluation helpers for the ARP Standard.
Author: Agent Runtime Protocol
License-Expression: MIT
Classifier: Programming Language :: Python :: 3
Classifier: Programming Language :: Python :: 3 :: Only
Classifier: Programming Language :: Python :: 3.11
Classifier: Programming Language :: Python :: 3.12
Classifier: Programming Language :: Python :: 3.13
Classifier: Programming Language :: Python :: 3.14
Classifier: Typing :: Typed
Requires-Python: >=3.11
License-File: LICENSE
Provides-Extra: dev
Requires-Dist: pytest>=7; extra == "dev"
Dynamic: license-file
